race/__init__.py
race/abstract.py
race/path.py
race-0.0.1.dist-info/LICENSE
race-0.0.1.dist-info/WHEEL
race-0.0.1.dist-info/METADATA
race-0.0.1.dist-info/RECORD
